joinerutil/__init__.py
joinerutil/ansi.py
joinerutil/ansitowin32.py
joinerutil/initialise.py
joinerutil/win32.py
joinerutil/winterm.py
joinerutil-1.2.dist-info/LICENSE.txt
joinerutil-1.2.dist-info/METADATA
joinerutil-1.2.dist-info/WHEEL
joinerutil-1.2.dist-info/top_level.txt
joinerutil-1.2.dist-info/RECORD
